[{"name":"start_processing.action_controller","payload":{"controller":"HomesController","action":"index","params":{"_":"1370682299905","page":"3","action":"index","controller":"homes"},"format":"js","method":"GET","path":"/homes?_=1370682299905&page=3"},"time":"2013-06-08T10:05:11+01:00","transaction_id":"326e4e69ba5b84a02e23","end":"2013-06-08T10:05:11+01:00","duration":0.003},{"name":"sql.active_record","payload":{"sql":"SELECT \"homes\".* FROM \"homes\" ","name":"Home Load","connection_id":70204046847180,"binds":[]},"time":"2013-06-08T10:05:11+01:00","transaction_id":"b6acea77a4a7a8ee8080","end":"2013-06-08T10:05:11+01:00","duration":0.125},{"name":"sql.active_record","payload":{"sql":"SELECT  \"puns\".* FROM \"puns\"  ORDER BY created_at DESC LIMIT 5 OFFSET 10","name":"Pun Load","connection_id":70204046847180,"binds":[]},"time":"2013-06-08T10:05:11+01:00","transaction_id":"b6acea77a4a7a8ee8080","end":"2013-06-08T10:05:11+01:00","duration":0.307},{"name":"sql.active_record","payload":{"sql":"SELECT COUNT(*) FROM \"puns\" ","name":null,"connection_id":70204046847180,"binds":[]},"time":"2013-06-08T10:05:11+01:00","transaction_id":"b6acea77a4a7a8ee8080","end":"2013-06-08T10:05:11+01:00","duration":0.147},{"name":"sql.active_record","payload":{"sql":"SELECT COUNT(*) FROM \"puns\"  WHERE (original_punaise_id = NULL)","name":null,"connection_id":70204046847180,"binds":[]},"time":"2013-06-08T10:05:11+01:00","transaction_id":"b6acea77a4a7a8ee8080","end":"2013-06-08T10:05:11+01:00","duration":0.114},{"name":"sql.active_record","payload":{"sql":"SELECT \"users\".* FROM \"users\"  WHERE \"users\".\"id\" IN (SELECT liker_id FROM \"likes\"  WHERE \"likes\".\"liker_type\" = 'User' AND \"likes\".\"likeable_type\" = 'Pun' AND \"likes\".\"likeable_id\" = 11)","name":"User Load","connection_id":70204046847180,"binds":[]},"time":"2013-06-08T10:05:11+01:00","transaction_id":"b6acea77a4a7a8ee8080","end":"2013-06-08T10:05:11+01:00","duration":0.134},{"name":"sql.active_record","payload":{"sql":"SELECT  \"users\".* FROM \"users\"  WHERE \"users\".\"id\" = 1 LIMIT 1","name":"User Load","connection_id":70204046847180,"binds":[]},"time":"2013-06-08T10:05:11+01:00","transaction_id":"b6acea77a4a7a8ee8080","end":"2013-06-08T10:05:11+01:00","duration":0.152},{"name":"sql.active_record","payload":{"sql":"SELECT  \"puns\".* FROM \"puns\"  WHERE (board_id = 1) LIMIT 1","name":"Pun Load","connection_id":70204046847180,"binds":[]},"time":"2013-06-08T10:05:11+01:00","transaction_id":"b6acea77a4a7a8ee8080","end":"2013-06-08T10:05:11+01:00","duration":0.155},{"name":"sql.active_record","payload":{"sql":"SELECT  \"boards\".* FROM \"boards\"  WHERE \"boards\".\"id\" = 1 LIMIT 1","name":"Board Load","connection_id":70204046847180,"binds":[]},"time":"2013-06-08T10:05:11+01:00","transaction_id":"b6acea77a4a7a8ee8080","end":"2013-06-08T10:05:11+01:00","duration":0.118},{"name":"sql.active_record","payload":{"sql":"SELECT  \"boards\".* FROM \"boards\"  WHERE \"boards\".\"id\" = 1 LIMIT 1","binds":[],"name":"CACHE","connection_id":70204046847180},"time":"2013-06-08T10:05:11+01:00","transaction_id":"326e4e69ba5b84a02e23","end":"2013-06-08T10:05:11+01:00","duration":0.001},{"name":"sql.active_record","payload":{"sql":"SELECT  \"users\".* FROM \"users\"  WHERE \"users\".\"id\" = 1 LIMIT 1","binds":[],"name":"CACHE","connection_id":70204046847180},"time":"2013-06-08T10:05:11+01:00","transaction_id":"326e4e69ba5b84a02e23","end":"2013-06-08T10:05:11+01:00","duration":0.001},{"name":"sql.active_record","payload":{"sql":"SELECT \"boards\".* FROM \"boards\"  WHERE (user_id = 1)","name":"Board Load","connection_id":70204046847180,"binds":[]},"time":"2013-06-08T10:05:11+01:00","transaction_id":"b6acea77a4a7a8ee8080","end":"2013-06-08T10:05:11+01:00","duration":0.108},{"name":"sql.active_record","payload":{"sql":"SELECT  \"puns\".* FROM \"puns\"  WHERE (board_id = 1) LIMIT 1","binds":[],"name":"CACHE","connection_id":70204046847180},"time":"2013-06-08T10:05:11+01:00","transaction_id":"326e4e69ba5b84a02e23","end":"2013-06-08T10:05:11+01:00","duration":0.001},{"name":"!render_template.action_view","payload":{"virtual_path":"puns/_pun"},"time":"2013-06-08T10:05:11+01:00","transaction_id":"326e4e69ba5b84a02e23","end":"2013-06-08T10:05:11+01:00","duration":14.696000000000002},{"name":"sql.active_record","payload":{"sql":"SELECT COUNT(*) FROM \"puns\"  WHERE (original_punaise_id = NULL)","binds":[],"name":"CACHE","connection_id":70204046847180},"time":"2013-06-08T10:05:11+01:00","transaction_id":"326e4e69ba5b84a02e23","end":"2013-06-08T10:05:11+01:00","duration":0.001},{"name":"sql.active_record","payload":{"sql":"SELECT \"users\".* FROM \"users\"  WHERE \"users\".\"id\" IN (SELECT liker_id FROM \"likes\"  WHERE \"likes\".\"liker_type\" = 'User' AND \"likes\".\"likeable_type\" = 'Pun' AND \"likes\".\"likeable_id\" = 10)","name":"User Load","connection_id":70204046847180,"binds":[]},"time":"2013-06-08T10:05:11+01:00","transaction_id":"b6acea77a4a7a8ee8080","end":"2013-06-08T10:05:11+01:00","duration":0.178},{"name":"sql.active_record","payload":{"sql":"SELECT  \"users\".* FROM \"users\"  WHERE \"users\".\"id\" = 1 LIMIT 1","binds":[],"name":"CACHE","connection_id":70204046847180},"time":"2013-06-08T10:05:11+01:00","transaction_id":"326e4e69ba5b84a02e23","end":"2013-06-08T10:05:11+01:00","duration":0.001},{"name":"sql.active_record","payload":{"sql":"SELECT  \"puns\".* FROM \"puns\"  WHERE (board_id = 2) LIMIT 1","name":"Pun Load","connection_id":70204046847180,"binds":[]},"time":"2013-06-08T10:05:11+01:00","transaction_id":"b6acea77a4a7a8ee8080","end":"2013-06-08T10:05:11+01:00","duration":0.135},{"name":"sql.active_record","payload":{"sql":"SELECT  \"boards\".* FROM \"boards\"  WHERE \"boards\".\"id\" = 2 LIMIT 1","name":"Board Load","connection_id":70204046847180,"binds":[]},"time":"2013-06-08T10:05:11+01:00","transaction_id":"b6acea77a4a7a8ee8080","end":"2013-06-08T10:05:11+01:00","duration":0.14300000000000002},{"name":"sql.active_record","payload":{"sql":"SELECT  \"boards\".* FROM \"boards\"  WHERE \"boards\".\"id\" = 2 LIMIT 1","binds":[],"name":"CACHE","connection_id":70204046847180},"time":"2013-06-08T10:05:11+01:00","transaction_id":"326e4e69ba5b84a02e23","end":"2013-06-08T10:05:11+01:00","duration":0.001},{"name":"sql.active_record","payload":{"sql":"SELECT \"boards\".* FROM \"boards\"  WHERE (user_id = 1)","binds":[],"name":"CACHE","connection_id":70204046847180},"time":"2013-06-08T10:05:11+01:00","transaction_id":"326e4e69ba5b84a02e23","end":"2013-06-08T10:05:11+01:00","duration":0.001},{"name":"sql.active_record","payload":{"sql":"SELECT  \"puns\".* FROM \"puns\"  WHERE (board_id = 2) LIMIT 1","binds":[],"name":"CACHE","connection_id":70204046847180},"time":"2013-06-08T10:05:11+01:00","transaction_id":"326e4e69ba5b84a02e23","end":"2013-06-08T10:05:11+01:00","duration":0.001},{"name":"!render_template.action_view","payload":{"virtual_path":"puns/_pun"},"time":"2013-06-08T10:05:11+01:00","transaction_id":"326e4e69ba5b84a02e23","end":"2013-06-08T10:05:11+01:00","duration":12.246},{"name":"sql.active_record","payload":{"sql":"SELECT COUNT(*) FROM \"puns\"  WHERE (original_punaise_id = NULL)","binds":[],"name":"CACHE","connection_id":70204046847180},"time":"2013-06-08T10:05:11+01:00","transaction_id":"326e4e69ba5b84a02e23","end":"2013-06-08T10:05:11+01:00","duration":0.001},{"name":"sql.active_record","payload":{"sql":"SELECT \"users\".* FROM \"users\"  WHERE \"users\".\"id\" IN (SELECT liker_id FROM \"likes\"  WHERE \"likes\".\"liker_type\" = 'User' AND \"likes\".\"likeable_type\" = 'Pun' AND \"likes\".\"likeable_id\" = 9)","name":"User Load","connection_id":70204046847180,"binds":[]},"time":"2013-06-08T10:05:11+01:00","transaction_id":"b6acea77a4a7a8ee8080","end":"2013-06-08T10:05:11+01:00","duration":0.23800000000000002},{"name":"sql.active_record","payload":{"sql":"SELECT  \"users\".* FROM \"users\"  WHERE \"users\".\"id\" = 1 LIMIT 1","binds":[],"name":"CACHE","connection_id":70204046847180},"time":"2013-06-08T10:05:11+01:00","transaction_id":"326e4e69ba5b84a02e23","end":"2013-06-08T10:05:11+01:00","duration":0.001},{"name":"sql.active_record","payload":{"sql":"SELECT  \"puns\".* FROM \"puns\"  WHERE (board_id = 1) LIMIT 1","binds":[],"name":"CACHE","connection_id":70204046847180},"time":"2013-06-08T10:05:11+01:00","transaction_id":"326e4e69ba5b84a02e23","end":"2013-06-08T10:05:11+01:00","duration":0.001},{"name":"sql.active_record","payload":{"sql":"SELECT  \"boards\".* FROM \"boards\"  WHERE \"boards\".\"id\" = 1 LIMIT 1","binds":[],"name":"CACHE","connection_id":70204046847180},"time":"2013-06-08T10:05:11+01:00","transaction_id":"326e4e69ba5b84a02e23","end":"2013-06-08T10:05:11+01:00","duration":0.002},{"name":"sql.active_record","payload":{"sql":"SELECT  \"boards\".* FROM \"boards\"  WHERE \"boards\".\"id\" = 1 LIMIT 1","binds":[],"name":"CACHE","connection_id":70204046847180},"time":"2013-06-08T10:05:11+01:00","transaction_id":"326e4e69ba5b84a02e23","end":"2013-06-08T10:05:11+01:00","duration":0.0},{"name":"sql.active_record","payload":{"sql":"SELECT \"boards\".* FROM \"boards\"  WHERE (user_id = 1)","binds":[],"name":"CACHE","connection_id":70204046847180},"time":"2013-06-08T10:05:11+01:00","transaction_id":"326e4e69ba5b84a02e23","end":"2013-06-08T10:05:11+01:00","duration":0.0},{"name":"sql.active_record","payload":{"sql":"SELECT  \"puns\".* FROM \"puns\"  WHERE (board_id = 1) LIMIT 1","binds":[],"name":"CACHE","connection_id":70204046847180},"time":"2013-06-08T10:05:11+01:00","transaction_id":"326e4e69ba5b84a02e23","end":"2013-06-08T10:05:11+01:00","duration":0.001},{"name":"!render_template.action_view","payload":{"virtual_path":"puns/_pun"},"time":"2013-06-08T10:05:11+01:00","transaction_id":"326e4e69ba5b84a02e23","end":"2013-06-08T10:05:11+01:00","duration":11.922},{"name":"sql.active_record","payload":{"sql":"SELECT COUNT(*) FROM \"puns\"  WHERE (original_punaise_id = NULL)","binds":[],"name":"CACHE","connection_id":70204046847180},"time":"2013-06-08T10:05:11+01:00","transaction_id":"326e4e69ba5b84a02e23","end":"2013-06-08T10:05:11+01:00","duration":0.001},{"name":"sql.active_record","payload":{"sql":"SELECT \"users\".* FROM \"users\"  WHERE \"users\".\"id\" IN (SELECT liker_id FROM \"likes\"  WHERE \"likes\".\"liker_type\" = 'User' AND \"likes\".\"likeable_type\" = 'Pun' AND \"likes\".\"likeable_id\" = 8)","name":"User Load","connection_id":70204046847180,"binds":[]},"time":"2013-06-08T10:05:11+01:00","transaction_id":"b6acea77a4a7a8ee8080","end":"2013-06-08T10:05:11+01:00","duration":0.182},{"name":"sql.active_record","payload":{"sql":"SELECT  \"users\".* FROM \"users\"  WHERE \"users\".\"id\" = 1 LIMIT 1","binds":[],"name":"CACHE","connection_id":70204046847180},"time":"2013-06-08T10:05:11+01:00","transaction_id":"326e4e69ba5b84a02e23","end":"2013-06-08T10:05:11+01:00","duration":0.001},{"name":"sql.active_record","payload":{"sql":"SELECT  \"puns\".* FROM \"puns\"  WHERE (board_id = 1) LIMIT 1","binds":[],"name":"CACHE","connection_id":70204046847180},"time":"2013-06-08T10:05:11+01:00","transaction_id":"326e4e69ba5b84a02e23","end":"2013-06-08T10:05:11+01:00","duration":0.0},{"name":"sql.active_record","payload":{"sql":"SELECT  \"boards\".* FROM \"boards\"  WHERE \"boards\".\"id\" = 1 LIMIT 1","binds":[],"name":"CACHE","connection_id":70204046847180},"time":"2013-06-08T10:05:11+01:00","transaction_id":"326e4e69ba5b84a02e23","end":"2013-06-08T10:05:11+01:00","duration":0.001},{"name":"sql.active_record","payload":{"sql":"SELECT  \"boards\".* FROM \"boards\"  WHERE \"boards\".\"id\" = 1 LIMIT 1","binds":[],"name":"CACHE","connection_id":70204046847180},"time":"2013-06-08T10:05:11+01:00","transaction_id":"326e4e69ba5b84a02e23","end":"2013-06-08T10:05:11+01:00","duration":0.001},{"name":"sql.active_record","payload":{"sql":"SELECT \"boards\".* FROM \"boards\"  WHERE (user_id = 1)","binds":[],"name":"CACHE","connection_id":70204046847180},"time":"2013-06-08T10:05:11+01:00","transaction_id":"326e4e69ba5b84a02e23","end":"2013-06-08T10:05:11+01:00","duration":0.001},{"name":"sql.active_record","payload":{"sql":"SELECT  \"puns\".* FROM \"puns\"  WHERE (board_id = 1) LIMIT 1","binds":[],"name":"CACHE","connection_id":70204046847180},"time":"2013-06-08T10:05:11+01:00","transaction_id":"326e4e69ba5b84a02e23","end":"2013-06-08T10:05:11+01:00","duration":0.0},{"name":"!render_template.action_view","payload":{"virtual_path":"puns/_pun"},"time":"2013-06-08T10:05:11+01:00","transaction_id":"326e4e69ba5b84a02e23","end":"2013-06-08T10:05:11+01:00","duration":11.632},{"name":"sql.active_record","payload":{"sql":"SELECT COUNT(*) FROM \"puns\"  WHERE (original_punaise_id = NULL)","binds":[],"name":"CACHE","connection_id":70204046847180},"time":"2013-06-08T10:05:11+01:00","transaction_id":"326e4e69ba5b84a02e23","end":"2013-06-08T10:05:11+01:00","duration":0.0},{"name":"sql.active_record","payload":{"sql":"SELECT \"users\".* FROM \"users\"  WHERE \"users\".\"id\" IN (SELECT liker_id FROM \"likes\"  WHERE \"likes\".\"liker_type\" = 'User' AND \"likes\".\"likeable_type\" = 'Pun' AND \"likes\".\"likeable_id\" = 5)","name":"User Load","connection_id":70204046847180,"binds":[]},"time":"2013-06-08T10:05:11+01:00","transaction_id":"b6acea77a4a7a8ee8080","end":"2013-06-08T10:05:11+01:00","duration":0.182},{"name":"sql.active_record","payload":{"sql":"SELECT  \"users\".* FROM \"users\"  WHERE \"users\".\"id\" = 1 LIMIT 1","binds":[],"name":"CACHE","connection_id":70204046847180},"time":"2013-06-08T10:05:11+01:00","transaction_id":"326e4e69ba5b84a02e23","end":"2013-06-08T10:05:11+01:00","duration":0.001},{"name":"sql.active_record","payload":{"sql":"SELECT  \"puns\".* FROM \"puns\"  WHERE (board_id = 2) LIMIT 1","binds":[],"name":"CACHE","connection_id":70204046847180},"time":"2013-06-08T10:05:11+01:00","transaction_id":"326e4e69ba5b84a02e23","end":"2013-06-08T10:05:11+01:00","duration":0.0},{"name":"sql.active_record","payload":{"sql":"SELECT  \"boards\".* FROM \"boards\"  WHERE \"boards\".\"id\" = 2 LIMIT 1","binds":[],"name":"CACHE","connection_id":70204046847180},"time":"2013-06-08T10:05:11+01:00","transaction_id":"326e4e69ba5b84a02e23","end":"2013-06-08T10:05:11+01:00","duration":0.001},{"name":"sql.active_record","payload":{"sql":"SELECT  \"boards\".* FROM \"boards\"  WHERE \"boards\".\"id\" = 2 LIMIT 1","binds":[],"name":"CACHE","connection_id":70204046847180},"time":"2013-06-08T10:05:11+01:00","transaction_id":"326e4e69ba5b84a02e23","end":"2013-06-08T10:05:11+01:00","duration":0.001},{"name":"sql.active_record","payload":{"sql":"SELECT \"boards\".* FROM \"boards\"  WHERE (user_id = 1)","binds":[],"name":"CACHE","connection_id":70204046847180},"time":"2013-06-08T10:05:11+01:00","transaction_id":"326e4e69ba5b84a02e23","end":"2013-06-08T10:05:11+01:00","duration":0.0},{"name":"sql.active_record","payload":{"sql":"SELECT  \"puns\".* FROM \"puns\"  WHERE (board_id = 2) LIMIT 1","binds":[],"name":"CACHE","connection_id":70204046847180},"time":"2013-06-08T10:05:11+01:00","transaction_id":"326e4e69ba5b84a02e23","end":"2013-06-08T10:05:11+01:00","duration":0.001},{"name":"!render_template.action_view","payload":{"virtual_path":"puns/_pun"},"time":"2013-06-08T10:05:11+01:00","transaction_id":"326e4e69ba5b84a02e23","end":"2013-06-08T10:05:11+01:00","duration":10.219000000000001},{"name":"render_collection.action_view","payload":{"identifier":"/Users/Hatchvenom/projects/punaise/app/views/puns/_pun.html.erb","count":5},"time":"2013-06-08T10:05:11+01:00","transaction_id":"326e4e69ba5b84a02e23","end":"2013-06-08T10:05:11+01:00","duration":61.032000000000004},{"name":"!render_template.action_view","payload":{"virtual_path":"homes/index"},"time":"2013-06-08T10:05:11+01:00","transaction_id":"326e4e69ba5b84a02e23","end":"2013-06-08T10:05:12+01:00","duration":1069.115},{"name":"render_template.action_view","payload":{"identifier":"/Users/Hatchvenom/projects/punaise/app/views/homes/index.js.erb","layout":null},"time":"2013-06-08T10:05:11+01:00","transaction_id":"326e4e69ba5b84a02e23","end":"2013-06-08T10:05:12+01:00","duration":1069.289},{"name":"process_action.action_controller","payload":{"controller":"HomesController","action":"index","params":{"_":"1370682299905","page":"3","action":"index","controller":"homes"},"format":"js","method":"GET","path":"/homes?_=1370682299905&page=3","status":200,"view_runtime":1069.337,"db_runtime":2.4409999999999976},"time":"2013-06-08T10:05:11+01:00","transaction_id":"326e4e69ba5b84a02e23","end":"2013-06-08T10:05:12+01:00","duration":1072.991}]